LICENSE
README.rst
setup.cfg
setup.py
tests/test_api.py
tests/test_cli.py
tests/test_payloads.py
usgs/__init__.py
usgs/api.py
usgs/payloads.py
usgs/xsi.py
usgs.egg-info/PKG-INFO
usgs.egg-info/SOURCES.txt
usgs.egg-info/dependency_links.txt
usgs.egg-info/entry_points.txt
usgs.egg-info/not-zip-safe
usgs.egg-info/requires.txt
usgs.egg-info/top_level.txt
usgs/data/datasets.json
usgs/scripts/__init__.py
usgs/scripts/cli.py