Metadata-Version: 2.4
Name: usgs
Version: 0.3.6
Summary: Access the USGS inventory service
Home-page: https://github.com/kapadia/usgs
Author: Amit Kapadia
Author-email: amit@planet.com
License: ISC
License-File: LICENSE
Requires-Dist: click>=4.0
Requires-Dist: requests>=2.7.0
Requires-Dist: requests_futures>=0.9.5
Provides-Extra: test
Requires-Dist: pytest; extra == "test"
Dynamic: author
Dynamic: author-email
Dynamic: home-page
Dynamic: keywords
Dynamic: license
Dynamic: license-file
Dynamic: provides-extra
Dynamic: requires-dist
Dynamic: summary
